{
    "$schema": "https://schema.management.azure.com/schemas/2019-04-01/deploymentParameters.json#",
    "contentVersion": "1.0.0.0",
    "parameters": {
        "acceleratedNetworking": {
            "value": "true"
          },            
        "environment":{
            "value": "prd"
        },        
        "appName":{
            "value": "forti"
        },
        "customer":{
            "value": "rim"
        },        
        "adminUsername": {
            "value": "kndadmin"
        },
        "adminPassword": {
            "value": "LEdffizEMtM8F3Pr"
        },
        "FortiGateNamePrefix": {
            "value": "rsazppap"
        },
        "FortiGateImageSKU": {
            "value": "fortinet_fg-vm"
        },
        "FortiGateImageVersion": {
            "value": "latest"
        },
        "instanceType": {
            "value": "Standard_F4s"
        },
        "publicIPNewOrExisting": {
            "value": "new"
        },
        "publicIPName": {
            "value": ""
        },
        "publicIPResourceGroup": {
            "value": "arsgrrimnvaeastusprd01"
        },
        "vnetNewOrExisting": {
            "value": "existing"
        },
        "vnetName": {
            "value": "avnetrimhubeastusprd01"
        },
        "vnetResourceGroup": {
            "value": "arsgrriminfeastusprd01"
        },
        "vnetAddressPrefix": {
            "value": "172.24.192.0/23"
        },
        "subnet1Name": {
            "value": "asnetpubhub01"
        },
        "subnet1Prefix": {
            "value": "172.24.192.64/26"
        },
        "subnet2Name": {
            "value": "asnetprvhub01"
        },
        "subnet2Prefix": {
            "value": "172.24.192.128/26"
        },
        "subnet3Name": {
            "value": "asnetsynhub01"
        },
        "subnet3Prefix": {
            "value": "172.24.192.224/27"
        },
        "subnet4Name": {
            "value": "asnetmgmhub01"
        },
        "subnet4Prefix": {
            "value": "172.24.192.192/27"
        },
        "subnet5Name": {
            "value": "asnetsvchub01"
        },
        "subnet5Prefix": {
            "value": "172.24.193.64/26"
        },                
        "location": {
            "value": "[resourceGroup().location]"
        },
        "FortinetTags": {
            "value": {
                "publisher": "Fortinet",
                "provider": "6EB3B02F-50E5-4A3E-8CB8-2E12925831AA-AZ"
            }
        }
    }
}